
[{"content":" 关于我 # 目前可公开的情报：\n搞CS的，是码农 目前在往全栈开发的方向努力，目前看来颇有成效 我的歌单 # 以下是一些我喜欢的音乐，希望你也喜欢：\n🎵 我的网易云歌单 ","date":"2024年11月18日","externalUrl":null,"permalink":"/about/","section":"昼梦日和","summary":"关于我和这个博客","title":"关于","type":"page"},{"content":"这里收录了博客的所有文章，按年份分类整理。\n","date":"2024年11月18日","externalUrl":null,"permalink":"/archives/","section":"昼梦日和","summary":"博客文章归档","title":"归档","type":"page"},{"content":" 摄影作品集 # 这里收录了我的一些摄影作品，记录生活中的美好瞬间。\n风景摄影 # 人像摄影 # 街拍摄影 # 建筑摄影 # 如何添加你的摄影作品 # 在 static/gallery/ 目录下创建你的图片文件夹 将图片文件放入相应文件夹 在上面的gallery shortcode中添加图片引用 使用 grid-wXX 类来控制图片宽度（10%-100%，5%递增） 可以使用响应式类如 md:grid-w33 lg:grid-w25 来适配不同屏幕 图片宽度参考 # grid-w100: 100%宽度，适合全景图 grid-w66: 66%宽度，适合横向构图 grid-w50: 50%宽度，标准尺寸 grid-w33: 33%宽度，三列布局 grid-w25: 25%宽度，四列布局 ","date":"2024年11月18日","externalUrl":null,"permalink":"/gallery/","section":"昼梦日和","summary":"我的摄影作品集","title":"摄影作品","type":"page"},{"content":"这里是我分享想法和经验的地方，记录生活中的点点滴滴，探索技术的无限可能。\nENTER MY DREAM ","date":"2024年11月18日","externalUrl":null,"permalink":"/","section":"昼梦日和","summary":"\u003cp\u003e这里是我分享想法和经验的地方，记录生活中的点点滴滴，探索技术的无限可能。\u003c/p\u003e\n\u003cp class=\"homepage-action-link\"\u003e\n    \u003ca class=\"link-hover-effect\" href=\"/posts/\"\u003e\n        ENTER MY DREAM\n    \u003c/a\u003e\n\u003c/p\u003e","title":"昼梦日和","type":"page"},{"content":"","date":"2024年3月20日","externalUrl":null,"permalink":"/categories/","section":"Categories","summary":"","title":"Categories","type":"categories"},{"content":"本文主要是想记录一下自己装修博客的过程，这次搭博客真的蛮快的，一天之内我就搞得七七八八了，这得归功于网上这么多的分享记录，所以我也来贡献一份自己的记录啦。\n2024.04.04 编辑：\n更新了【修改链接样式】部分的代码，最新版本代码限制了只在正文和目录里会应用样式。 更新了友链卡片的css代码，原代码关于设置链接样式的部分其实没有生效，debug的时候发现后就赶紧改过来了（ 2024.05.24 编辑：\n给以前的装修加上效果图 搭建博客 # 我已经确定博客框架选择Hugo，因为最多人用（虽然我也不太确定，但是身边人确实大部分都用的是Hugo），这样Debug方便，抄别人的装修作业也很方便（x）\n挑选主题 # 我个人觉得搭建博客第一步就是先选主题，因为每个主题都会有自己的教程，跟着主题的官方教程走，出错的概率非常小。我挑选主题时最看重三个要素：\n使用人数多不多。 这个优先级最高，因为虽然我是程序员，但我也不太喜欢花太多时间和精力在Debug或者自己造轮子上面。如果选择很多人都在用的主题，自己遇到的问题大概率别人已经遇到并解决了。 完美支持Markdown，并能优雅美丽地展示Markdown。 有些博客虽然很美丽，但只会美丽地展示一部分的Markdown元素，这些博客都会直接被我pass掉。 有提供足够的自定义空间。我知道受欢迎的博客肯定也是经过多次设计迭代、被市场证明的美丽博客，但是不可能要求它全部内容都符合自己的审美，所以肯定是要自己改动一部分的。 版本和开发工具 # 写此博客时，我的配置如下：\nHugo版本：v0.145.0\nBlowFish版本：2.84.0\n命令行工具：Warp\n开发工具：Webstorm\n操作系统：MacOS\n如果直接复制我文中提到的代码后出错了，记得查看版本是否一致哦^ ^\n装修博客 # 搭建首页 # 我把首页文件放在layouts/index.html，BlowFish文档中说自定义首页文件要放在layouts/partials/home/custom.html，我实验了一下，效果是一样的。以下是我的首页代码：\n{{ define \u0026#34;main\u0026#34; }} \u0026lt;main class=\u0026#34;w-full mt-20 px-6\u0026#34;\u0026gt; \u0026lt;section class=\u0026#34;flex flex-col lg:flex-row items-center justify-between gap-16 max-w-6xl mx-auto\u0026#34;\u0026gt; \u0026lt;!-- 图片区块 --\u0026gt; \u0026lt;div class=\u0026#34;lg:w-1/2 order-first lg:order-none shrink-0\u0026#34;\u0026gt; {{ with .Params.images }} {{ range first 1 . }} \u0026lt;img width=\u0026#34;650\u0026#34; src=\u0026#34;{{ . }}\u0026#34; alt=\u0026#34;Background\u0026#34; class=\u0026#34;mx-auto rounded-xl shadow-md object-contain\u0026#34; /\u0026gt; {{ end }} {{ end }} \u0026lt;/div\u0026gt; \u0026lt;!-- 文字区块 --\u0026gt; \u0026lt;div class=\u0026#34;lg:w-1/2 text-right flex flex-col justify-center\u0026#34;\u0026gt; {{ with .Params.title }} \u0026lt;h1 class=\u0026#34;text-4xl lg:text-5xl font-semibold mb-4 leading-tight max-w-md mx-auto lg:mx-0\u0026#34;\u0026gt;{{ . }}\u0026lt;/h1\u0026gt; {{ end }} {{ with .Params.subtitle }} \u0026lt;h2 class=\u0026#34;text-sm uppercase tracking-widest font-bold text-gray-500 mb-6 max-w-md mx-auto lg:mx-0\u0026#34;\u0026gt;{{ . }}\u0026lt;/h2\u0026gt; {{ end }} {{ with .Params.description }} \u0026lt;p class=\u0026#34;text-lg text-gray-700 mb-8 mt-6 leading-relaxed max-w-md mx-auto lg:mx-0 whitespace-nowrap\u0026#34;\u0026gt;{{ . | markdownify }}\u0026lt;/p\u0026gt; {{ end }} \u0026lt;/div\u0026gt; \u0026lt;/section\u0026gt; \u0026lt;/main\u0026gt; {{ end }} 修改字体 # 我使用的字体列表如下：\n中文标题：花园明朝体 中文正文：方正书宋体 英文标题：Fraunces 英文正文：Commissioner 每次下载字体时最好下载GBK版，意思是简繁体都适用，以及最好把字体格式转换为WOFF2，性能最佳。\n在我修改完字体以后，页面中所有文字部分莫名变窄了，询问了GPT以后，它猜测是因为主题内定义的max-w-prose或max-w-*限制了容器宽度，我检查了一下，果然发现主题默认写了max-w-prose，它会把正文区域的最大宽度限制在65ch（大约65个字符宽），于是我加了个代码取消掉了这个限制：\n.max-w-prose { max-width: none !important; } 总结 # 这么写下来，发现自己确实没怎么改动原主题呢，但是样式却跟原主题几乎两模两样，这就是UI的魅力吧！\n","date":"2024年3月20日","externalUrl":null,"permalink":"/posts/hugo-blog-styling/","section":"Posts","summary":"记录一下自己装修博客的过程，这次搭博客真的蛮快的","title":"Hugo + Blowfish | 自装样式记录","type":"posts"},{"content":"","date":"2024年3月20日","externalUrl":null,"permalink":"/posts/","section":"Posts","summary":"","title":"Posts","type":"posts"},{"content":"","date":"2024年3月20日","externalUrl":null,"permalink":"/tags/","section":"Tags","summary":"","title":"Tags","type":"tags"},{"content":"","date":"2024年3月20日","externalUrl":null,"permalink":"/categories/tech/","section":"Categories","summary":"","title":"Tech","type":"categories"},{"content":"","date":"2024年3月20日","externalUrl":null,"permalink":"/tags/%E5%8D%9A%E5%AE%A2%E7%9B%B8%E5%85%B3/","section":"Tags","summary":"","title":"博客相关","type":"tags"},{"content":"","externalUrl":null,"permalink":"/authors/","section":"Authors","summary":"","title":"Authors","type":"authors"},{"content":"","externalUrl":null,"permalink":"/series/","section":"Series","summary":"","title":"Series","type":"series"}]